casagui/LICENSE.rst
casagui/__icons__/20px/fast-backward.svg
casagui/__icons__/20px/fast-forward.svg
casagui/__icons__/20px/step-backward.svg
casagui/__icons__/20px/step-forward.svg
casagui/__icons__/add-chan.png
casagui/__icons__/add-chan.svg
casagui/__icons__/add-cube.png
casagui/__icons__/add-cube.svg
casagui/__icons__/drag.png
casagui/__icons__/drag.svg
casagui/__icons__/mask-selected.png
casagui/__icons__/mask.png
casagui/__icons__/mask.svg
casagui/__icons__/new-layer-sm-selected.png
casagui/__icons__/new-layer-sm-selected.svg
casagui/__icons__/new-layer-sm.png
casagui/__icons__/new-layer-sm.svg
casagui/__icons__/reset.png
casagui/__icons__/reset.svg
casagui/__icons__/sub-chan.png
casagui/__icons__/sub-chan.svg
casagui/__icons__/sub-cube.png
casagui/__icons__/sub-cube.svg
casagui/__icons__/zoom-to-fit.png
casagui/__icons__/zoom-to-fit.svg
casagui/__init__.py
casagui/__js__/bokeh-3.6.1.min.js
casagui/__js__/bokeh-tables-3.6.1.min.js
casagui/__js__/bokeh-widgets-3.6.1.min.js
casagui/__js__/casaguijs.min.js
casagui/__js__/casalib.min.js
casagui/apps/__init__.py
casagui/apps/_createmask.py
casagui/apps/_createregion.py
casagui/apps/_interactiveclean.py
casagui/apps/_interactiveclean_wrappers.py
casagui/apps/_ms_raster.py
casagui/apps/_plotants.py
casagui/apps/_plotbandpass.py
casagui/bokeh/__init__.py
casagui/bokeh/annotations/__init__.py
casagui/bokeh/annotations/_ev_poly_annotation.py
casagui/bokeh/components/__init__.py
casagui/bokeh/format/__init__.py
casagui/bokeh/format/_time_ticks.py
casagui/bokeh/format/_wcs_ticks.py
casagui/bokeh/models/__init__.py
casagui/bokeh/models/_edit_span.py
casagui/bokeh/models/_ev_text_input.py
casagui/bokeh/models/_tip.py
casagui/bokeh/models/_tip_button.py
casagui/bokeh/sources/__init__.py
casagui/bokeh/sources/_data_pipe.py
casagui/bokeh/sources/_image_data_source.py
casagui/bokeh/sources/_image_pipe.py
casagui/bokeh/sources/_spectra_data_source.py
casagui/bokeh/sources/_updatable_data_source.py
casagui-0.4.3.dist-info/WHEEL
casagui-0.4.3.dist-info/METADATA
casagui-0.4.3.dist-info/licenses/LICENSE
casagui-0.4.3.dist-info/RECORD
