Metadata-Version: 2.1
Name: casagui
Version: 0.4.3
Summary: visualization toolkit and apps for casa
License: LGPL
Author-email: Darrell Schiebel <darrell@schiebel.us>,Pam Harris <pharris@nrao.edu>
Requires-Python: >=3.10
Requires-Dist: astropy>=5.1
Requires-Dist: bokeh==3.6.1
Requires-Dist: certifi
Requires-Dist: matplotlib
Requires-Dist: regions>=0.6
Requires-Dist: websockets>=10.3
